odoo/addons/project_task_pull_request/README.rst
odoo/addons/project_task_pull_request/__init__.py
odoo/addons/project_task_pull_request/__manifest__.py
odoo/addons/project_task_pull_request/i18n/ar.po
odoo/addons/project_task_pull_request/i18n/ca.po
odoo/addons/project_task_pull_request/i18n/de.po
odoo/addons/project_task_pull_request/i18n/el.po
odoo/addons/project_task_pull_request/i18n/es.po
odoo/addons/project_task_pull_request/i18n/es_CR.po
odoo/addons/project_task_pull_request/i18n/es_MX.po
odoo/addons/project_task_pull_request/i18n/es_VE.po
odoo/addons/project_task_pull_request/i18n/fi.po
odoo/addons/project_task_pull_request/i18n/fr.po
odoo/addons/project_task_pull_request/i18n/gl.po
odoo/addons/project_task_pull_request/i18n/hr.po
odoo/addons/project_task_pull_request/i18n/hr_HR.po
odoo/addons/project_task_pull_request/i18n/hu.po
odoo/addons/project_task_pull_request/i18n/it.po
odoo/addons/project_task_pull_request/i18n/ja.po
odoo/addons/project_task_pull_request/i18n/lt.po
odoo/addons/project_task_pull_request/i18n/lv.po
odoo/addons/project_task_pull_request/i18n/mk.po
odoo/addons/project_task_pull_request/i18n/mn.po
odoo/addons/project_task_pull_request/i18n/nl.po
odoo/addons/project_task_pull_request/i18n/nl_NL.po
odoo/addons/project_task_pull_request/i18n/pl.po
odoo/addons/project_task_pull_request/i18n/project_task_pull_request.pot
odoo/addons/project_task_pull_request/i18n/pt.po
odoo/addons/project_task_pull_request/i18n/pt_BR.po
odoo/addons/project_task_pull_request/i18n/pt_PT.po
odoo/addons/project_task_pull_request/i18n/ro.po
odoo/addons/project_task_pull_request/i18n/sl.po
odoo/addons/project_task_pull_request/i18n/sv.po
odoo/addons/project_task_pull_request/i18n/tr.po
odoo/addons/project_task_pull_request/i18n/uk.po
odoo/addons/project_task_pull_request/i18n/zh_CN.po
odoo/addons/project_task_pull_request/models/__init__.py
odoo/addons/project_task_pull_request/models/project_project.py
odoo/addons/project_task_pull_request/models/project_task.py
odoo12_addon_project_task_pull_request-12.0.1.1.0.dist-info/METADATA
odoo12_addon_project_task_pull_request-12.0.1.1.0.dist-info/WHEEL
odoo12_addon_project_task_pull_request-12.0.1.1.0.dist-info/top_level.txt
odoo12_addon_project_task_pull_request-12.0.1.1.0.dist-info/RECORD
